SoftwareConstructionLectureNotesMit6005/README.md
SoftwareConstructionLectureNotesMit6005/__init__.py
SoftwareConstructionLectureNotesMit6005/__main__.py
SoftwareConstructionLectureNotesMit6005/file.epub
SoftwareConstructionLectureNotesMit6005/index.html
SoftwareConstructionLectureNotesMit6005/css/__init__.py
SoftwareConstructionLectureNotesMit6005/css/annotations.css
SoftwareConstructionLectureNotesMit6005/css/main.css
SoftwareConstructionLectureNotesMit6005/css/normalize.css
SoftwareConstructionLectureNotesMit6005/css/popup.css
SoftwareConstructionLectureNotesMit6005/font/__init__.py
SoftwareConstructionLectureNotesMit6005/font/fontello.eot
SoftwareConstructionLectureNotesMit6005/font/fontello.svg
SoftwareConstructionLectureNotesMit6005/font/fontello.ttf
SoftwareConstructionLectureNotesMit6005/font/fontello.woff
SoftwareConstructionLectureNotesMit6005/img/__init__.py
SoftwareConstructionLectureNotesMit6005/img/annotator-glyph-sprite.png
SoftwareConstructionLectureNotesMit6005/img/annotator-icon-sprite.png
SoftwareConstructionLectureNotesMit6005/img/apple-touch-icon.png
SoftwareConstructionLectureNotesMit6005/img/cancelfullscreen.png
SoftwareConstructionLectureNotesMit6005/img/close.png
SoftwareConstructionLectureNotesMit6005/img/fullscreen.png
SoftwareConstructionLectureNotesMit6005/img/loader.gif
SoftwareConstructionLectureNotesMit6005/img/menu-icon.png
SoftwareConstructionLectureNotesMit6005/img/save.png
SoftwareConstructionLectureNotesMit6005/img/saved.png
SoftwareConstructionLectureNotesMit6005/img/settings-s.png
SoftwareConstructionLectureNotesMit6005/img/settings.png
SoftwareConstructionLectureNotesMit6005/img/star.png
SoftwareConstructionLectureNotesMit6005/js/__init__.py
SoftwareConstructionLectureNotesMit6005/js/epub.js
SoftwareConstructionLectureNotesMit6005/js/epub.min.js
SoftwareConstructionLectureNotesMit6005/js/epub.min.map
SoftwareConstructionLectureNotesMit6005/js/hooks.min.js
SoftwareConstructionLectureNotesMit6005/js/hooks.min.map
software_construction_lecture_notes_mit_6_005-2024.3.2.0.dist-info/METADATA
software_construction_lecture_notes_mit_6_005-2024.3.2.0.dist-info/WHEEL
software_construction_lecture_notes_mit_6_005-2024.3.2.0.dist-info/entry_points.txt
software_construction_lecture_notes_mit_6_005-2024.3.2.0.dist-info/top_level.txt
software_construction_lecture_notes_mit_6_005-2024.3.2.0.dist-info/RECORD
